dynamic_batcher/__init__.py
dynamic_batcher/__main__.py
dynamic_batcher/batcher.py
dynamic_batcher/logger.py
dynamic_batcher/redis_engine.py
dynamic_batcher/types.py
dynamic_batcher/validate.py
dynamic_batcher-1.0.6.1.dist-info/METADATA
dynamic_batcher-1.0.6.1.dist-info/WHEEL
dynamic_batcher-1.0.6.1.dist-info/entry_points.txt
dynamic_batcher-1.0.6.1.dist-info/top_level.txt
dynamic_batcher-1.0.6.1.dist-info/RECORD
