Metadata-Version: 2.1
Name: dynamic-batcher
Version: 1.0.6.1
Summary: A daemon processor for gathering requests into a batch.
Author-email: Youngju Jaden Kim <pydemia@gmail.com>
Project-URL: Homepage, https://dynamic-batcher.readthedocs.io/en/latest/
Project-URL: Repository, https://github.com/pydemia/dynamic-batcher
Project-URL: Changelog, https://github.com/pydemia/dynamic-batcher/CHANGELOG.md
Project-URL: Bug Tracker, https://github.com/pydemia/dynamic-batcher/issues
Classifier: Programming Language :: Python :: 3
Classifier: License :: OSI Approved :: MIT License
Classifier: Operating System :: OS Independent
Classifier: Development Status :: 5 - Production/Stable
Requires-Python: >=3.9
Requires-Dist: redis
Requires-Dist: autologging
Provides-Extra: dev
Requires-Dist: setuptools ; extra == 'dev'
Requires-Dist: wheel ; extra == 'dev'
Requires-Dist: twine ; extra == 'dev'
Requires-Dist: build ; extra == 'dev'
Requires-Dist: sphinx ; extra == 'dev'
Requires-Dist: sphinx-rtd-theme ; extra == 'dev'
Provides-Extra: test
Requires-Dist: pytest ; extra == 'test'
Requires-Dist: fastapi ; extra == 'test'
Requires-Dist: locust ; extra == 'test'
Requires-Dist: python-dotenv ; extra == 'test'
Requires-Dist: gunicorn ; extra == 'test'
Requires-Dist: uvicorn ; extra == 'test'
